Topsis_Ujjwal_101916067/Topsis-Ujjwal-101916067.py
Topsis_Ujjwal_101916067/__init__.py
Topsis_Ujjwal_101916067/topsis.py
Topsis_Ujjwal_101916067-1.8.dist-info/METADATA
Topsis_Ujjwal_101916067-1.8.dist-info/WHEEL
Topsis_Ujjwal_101916067-1.8.dist-info/top_level.txt
Topsis_Ujjwal_101916067-1.8.dist-info/RECORD
